MANIFEST.in
README.md
README.rst
setup.py
xart/__init__.py
xart/errors.py
xart/font.py
xart/renderer.py
xart.egg-info/PKG-INFO
xart.egg-info/SOURCES.txt
xart.egg-info/dependency_links.txt
xart.egg-info/entry_points.txt
xart.egg-info/top_level.txt
xart/fonts/1Row.flf
xart/fonts/3-D.flf
xart/fonts/3D-ASCII.flf
xart/fonts/3D_Diagonal.flf
xart/fonts/3x5.flf
xart/fonts/4Max.flf
xart/fonts/5LineOblique.flf
xart/fonts/AMC3Line.flf
xart/fonts/AMC3Liv1.flf
xart/fonts/AMCAAA01.flf
xart/fonts/AMCNeko.flf
xart/fonts/AMCRazor.flf
xart/fonts/AMCRazor2.flf
xart/fonts/AMCSlash.flf
xart/fonts/AMCSlider.flf
xart/fonts/AMCThin.flf
xart/fonts/AMCTubes.flf
xart/fonts/AMCUntitled.flf
xart/fonts/ANSI_Shadow.flf
xart/fonts/ASCIINewRoman.flf
xart/fonts/Acrobatic.flf
xart/fonts/Alligator.flf
xart/fonts/Alligator2.flf
xart/fonts/Alpha.flf
xart/fonts/Alphabet.flf
xart/fonts/Arrows.flf
xart/fonts/Avatar.flf
xart/fonts/Banner.flf
xart/fonts/Banner3-D.flf
xart/fonts/Banner3.flf
xart/fonts/Banner4.flf
xart/fonts/Barbwire.flf
xart/fonts/Basic.flf
xart/fonts/Bear.flf
xart/fonts/Bell.flf
xart/fonts/Benjamin.flf
xart/fonts/Big.flf
xart/fonts/BigChief.flf
xart/fonts/BigMoney-ne.flf
xart/fonts/BigMoney-nw.flf
xart/fonts/BigMoney-se.flf
xart/fonts/BigMoney-sw.flf
xart/fonts/Bigfig.flf
xart/fonts/Binary.flf
xart/fonts/Block.flf
xart/fonts/Blocks.flf
xart/fonts/Bloody.flf
xart/fonts/Bolger.flf
xart/fonts/Braced.flf
xart/fonts/Bright.flf
xart/fonts/Broadway.flf
xart/fonts/BroadwayKB.flf
xart/fonts/Bubble.flf
xart/fonts/Bulbhead.flf
xart/fonts/Caligraphy.flf
xart/fonts/Caligraphy2.flf
xart/fonts/CalvinS.flf
xart/fonts/Cards.flf
xart/fonts/Catwalk.flf
xart/fonts/Chiseled.flf
xart/fonts/Chunky.flf
xart/fonts/Coinstak.flf
xart/fonts/Cola.flf
xart/fonts/Colossal.flf
xart/fonts/Computer.flf
xart/fonts/Contessa.flf
xart/fonts/Contrast.flf
xart/fonts/Cosmike.flf
xart/fonts/Crawford.flf
xart/fonts/Crawford2.flf
xart/fonts/Crazy.flf
xart/fonts/Cricket.flf
xart/fonts/Cursive.flf
xart/fonts/Cyberlarge.flf
xart/fonts/Cybermedium.flf
xart/fonts/Cybersmall.flf
xart/fonts/Cygnet.flf
xart/fonts/DANC4.flf
xart/fonts/DWhistled.flf
xart/fonts/DancingFont.flf
