Metadata-Version: 1.1
Name: xart
Version: 0.2.0
Summary: generate art ascii texts
Home-page: https://github.com/xlzd/xart
Author: xlzd
Author-email: i@xlzd.me
License: WTFPL
Platform: UNKNOWN
Classifier: Environment :: Console
Classifier: Programming Language :: Python
Classifier: Topic :: Text Processing :: Fonts
